public/__init__.py
public/cifra10/__init__.py
public/mnist/__init__.py
public/svhn/__init__.py
public_datasets-0.0.2.dist-info/LICENSE
public_datasets-0.0.2.dist-info/METADATA
public_datasets-0.0.2.dist-info/WHEEL
public_datasets-0.0.2.dist-info/entry_points.txt
public_datasets-0.0.2.dist-info/top_level.txt
public_datasets-0.0.2.dist-info/RECORD
